dockersh/__init__.py
dockersh/commands.py
dockersh/completer.py
dockersh/main.py
dockersh-0.0.2.dist-info/AUTHORS.rst
dockersh-0.0.2.dist-info/LICENSE
dockersh-0.0.2.dist-info/METADATA
dockersh-0.0.2.dist-info/WHEEL
dockersh-0.0.2.dist-info/entry_points.txt
dockersh-0.0.2.dist-info/top_level.txt
dockersh-0.0.2.dist-info/RECORD
